setup.py
rest_framework_cache/__init__.py
rest_framework_cache/cache.py
rest_framework_cache/exceptions.py
rest_framework_cache/registry.py
rest_framework_cache/serializers.py
rest_framework_cache/settings.py
rest_framework_cache/signals.py
rest_framework_cache/utils.py
rest_framework_cache.egg-info/PKG-INFO
rest_framework_cache.egg-info/SOURCES.txt
rest_framework_cache.egg-info/dependency_links.txt
rest_framework_cache.egg-info/namespace_packages.txt
rest_framework_cache.egg-info/top_level.txt
tests/__init__.py
tests/models.py
tests/serializers.py
tests/tests_cache.py
tests/tests_registry.py
tests/tests_serializers.py
tests/tests_utils.py