Metadata-Version: 1.1
Name: rest-framework-cache
Version: 0.1
Summary: Easy to use cache framework for django-rest-framwork apps
Home-page: https://github.com/ervilis/django-rest-framework-cache/
Author: Ervilis Souza
Author-email: ervilisviana@gmail.com
License: GPLv3
Download-URL: https://github.com/ervilis/django-rest-framework-cache//tarball/master
Keywords: rest_framework_cache
Platform: UNKNOWN
Classifier: Development Status :: 3 - Alpha
Classifier: Framework :: Django
Classifier: Topic :: Utilities
Classifier: Environment :: Plugins
Classifier: License :: OSI Approved :: GNU General Public License v3 (GPLv3)
Classifier: Operating System :: OS Independent
Classifier: Intended Audience :: Developers
